<?xml version="1.0" encoding="UTF-8"?>
<objects serializationModel="Studio.02.02.00">
	<object class="AudioFile" id="{1ea97f3a-b74f-4d56-949c-9163b0b5af71}">
		<property name="assetPath">
			<value>Mansion Hallways Loop.mp3</value>
		</property>
		<property name="isStreaming">
			<value>true</value>
		</property>
		<property name="frequencyInKHz">
			<value>44.0999985</value>
		</property>
		<property name="channelCount">
			<value>2</value>
		</property>
		<property name="length">
			<value>180.14040816326531</value>
		</property>
		<relationship name="masterAssetFolder">
			<destination>{cd068cb8-d2c8-4959-8ff9-8fcca07c944e}</destination>
		</relationship>
	</object>
</objects>
